pennylane_snowflurry/__init__.py
pennylane_snowflurry/_version.py
pennylane_snowflurry/execution_config.py
pennylane_snowflurry/julia_setup.py
pennylane_snowflurry/pennylane_converter.py
pennylane_snowflurry/snowflurry_device.py
pennylane_snowflurry/measurements/__init__.py
pennylane_snowflurry/measurements/counts.py
pennylane_snowflurry/measurements/expectation_value.py
pennylane_snowflurry/measurements/measurement_strategy.py
pennylane_snowflurry/measurements/probabilities.py
pennylane_snowflurry/measurements/sample.py
pennylane_snowflurry/measurements/state.py
pennylane_snowflurry-0.4.3.dist-info/LICENSE
pennylane_snowflurry-0.4.3.dist-info/METADATA
pennylane_snowflurry-0.4.3.dist-info/WHEEL
pennylane_snowflurry-0.4.3.dist-info/entry_points.txt
pennylane_snowflurry-0.4.3.dist-info/top_level.txt
pennylane_snowflurry-0.4.3.dist-info/RECORD
