Metadata-Version: 2.1
Name: pennylane-snowflurry
Version: 0.4.3
Summary: PennyLane plugin for interfacing with Anyon's quantum computers
Maintainer-email: Calcul Québec <support@tech.alliancecan.ca>
License: Apache Software License (Apache License 2.0)
Project-URL: Source, https://github.com/calculquebec/pennylane-snowflurry
Classifier: Development Status :: 3 - Alpha
Classifier: Environment :: Console
Classifier: Intended Audience :: Science/Research
Classifier: License :: OSI Approved :: Apache Software License
Classifier: Natural Language :: English
Classifier: Operating System :: POSIX
Classifier: Operating System :: MacOS :: MacOS X
Classifier: Operating System :: POSIX :: Linux
Classifier: Operating System :: Microsoft :: Windows
Classifier: Programming Language :: Python
Classifier: Programming Language :: Python :: 3
Classifier: Programming Language :: Python :: 3.9
Classifier: Programming Language :: Python :: 3.10
Classifier: Programming Language :: Python :: 3.11
Classifier: Programming Language :: Python :: 3 :: Only
Classifier: Topic :: Scientific/Engineering :: Physics
Requires-Python: >=3.9
License-File: LICENSE
Requires-Dist: numpy
Requires-Dist: juliacall >=0.9.0
Requires-Dist: pennylane >=0.30.0
Provides-Extra: test
Requires-Dist: matplotlib ; extra == 'test'
Requires-Dist: pytest ; extra == 'test'
Requires-Dist: pytest-mock ; extra == 'test'
Requires-Dist: flaky ; extra == 'test'
